synkka/__about__.py
synkka/__init__.py
synkka/exceptions.py
synkka/iterators.py
synkka/types.py
synkka/utilities.py
synkka-0.0.1.dist-info/METADATA
synkka-0.0.1.dist-info/WHEEL
synkka-0.0.1.dist-info/licenses/LICENSE.txt
synkka-0.0.1.dist-info/RECORD
